DSE3testInstaller/__init__.py
DSE3testInstaller/mainos.exe
dse3testinstaller-0.1.0.dist-info/METADATA
dse3testinstaller-0.1.0.dist-info/WHEEL
dse3testinstaller-0.1.0.dist-info/top_level.txt
dse3testinstaller-0.1.0.dist-info/RECORD
