Metadata-Version: 2.4
Name: DSE3testInstaller
Version: 0.1.0
Summary: A package that includes a standalone EXE
Author: Krishna kanth
Author-email: krishnakanth6768@gmail.com
Classifier: Programming Language :: Python :: 3
Dynamic: author
Dynamic: author-email
Dynamic: classifier
Dynamic: description
Dynamic: description-content-type
Dynamic: summary
